{
  "algorithm_name": "GES(local_score_BIC)",
  "safe_name": "GES_local_score_BIC_",
  "elapsed_time": 0.8811089992523193,
  "metrics": {
    "adj_precision": 0.29545454545454547,
    "adj_recall": 0.6842105263157895,
    "f1_adj": 0.41269841269841273,
    "arrow_precision": NaN,
    "arrow_recall": 0.0,
    "f1_arrow": NaN,
    "shd": 50.0
  },
  "error": null,
  "graph_path": "results/monetary_longrun/graphs/graph_GES_local_score_BIC_.txt",
  "graph_json_path": "results/monetary_longrun/graphs/graph_GES_local_score_BIC_.json",
  "edges": 44,
  "created_at": "2025-12-04T17:26:55.664061Z"
}